LICENSE
README.md
setup.py
apgw/__init__.py
apgw/builder.py
apgw/connection_wrapper.py
apgw/constraint.py
apgw/exceptions.py
apgw/py.typed
apgw/types.py
apgw/util.py
apgw.egg-info/PKG-INFO
apgw.egg-info/SOURCES.txt
apgw.egg-info/dependency_links.txt
apgw.egg-info/not-zip-safe
apgw.egg-info/requires.txt
apgw.egg-info/top_level.txt