Metadata-Version: 2.1
Name: apgw
Version: 0.0.43
Summary: A simple wrapper around asyncpg to make some common actions simpler.
Home-page: https://gitlab.com/tcucco/apgw
Download-URL: https://gitlab.com/tcucco/apgw/-/archive/master/apgw-master.tar.gz
Author: Trey Cucco
Author-email: fcucco@gmail.com
License: MIT
Platform: any
Classifier: Development Status :: 4 - Beta
Classifier: Intended Audience :: Developers
Classifier: License :: OSI Approved :: MIT License
Classifier: Natural Language :: English
Classifier: Operating System :: OS Independent
Classifier: Programming Language :: Python :: 3.7
License-File: LICENSE
